{"flamingo": 12, "cat": 193, "kiwi": 33, "hedgehog": 51, "blood kiwi": 27, "snail": 30, "bee": 640, "disco bee": 367, "mimic octopus": 281, "red fox": 314, "owl": 241, "scarlet macaw": 66, "moon cat": 157, "bear bee": 69, "moth": 71, "seal": 92, "cooked owl": 175, "queen bee": 328, "dragonfly": 329, "raccoon": 505, "butterfly": 324, "blood hedgehog": 31, "giant ant": 29, "praying mantis": 35, "caterpillar": 10, "chicken zombie": 108, "chicken": 197, "silver monkey": 17, "monkey": 20, "frog": 21, "orangutan": 19, "toucan": 38, "echo frog": 12, "deer": 4, "polar bear": 27, "squirrel": 14, "petal bee": 38, "turtle": 31, "sea turtle": 17, "capybara": 51, "brown mouse": 6, "red giant ant": 9, "peacock": 28, "tarantula hawk": 20, "night owl": 44, "golden lab": 13, "dog": 16, "honey bee": 8, "grey mouse": 7, "ostrich": 17, "starfish": 12, "pig": 2, "sea otter": 2, "orange tabby": 3, "crab": 13, "seagull": 4, "pack bee": 19, "wasp": 9, "bunny": 5, "cow": 13, "mole": 30, "blood owl": 38, "rooster": 3, "panda": 9}